README.txt
setup.cfg
setup.py
docs/CHANGES.txt
docs/INSTALL.txt
docs/LICENSE.txt
p4a/__init__.py
p4a.fileimage.egg-info/PKG-INFO
p4a.fileimage.egg-info/SOURCES.txt
p4a.fileimage.egg-info/dependency_links.txt
p4a.fileimage.egg-info/entry_points.txt
p4a.fileimage.egg-info/namespace_packages.txt
p4a.fileimage.egg-info/not-zip-safe
p4a.fileimage.egg-info/requires.txt
p4a.fileimage.egg-info/top_level.txt
p4a/fileimage/__init__.py
p4a/fileimage/_property.py
p4a/fileimage/browser.py
p4a/fileimage/configure.zcml
p4a/fileimage/file.txt
p4a/fileimage/tests.py
p4a/fileimage/utils.py
p4a/fileimage/file/__init__.py
p4a/fileimage/file/_field.py
p4a/fileimage/file/_property.py
p4a/fileimage/file/_widget.py
p4a/fileimage/file/configure.zcml
p4a/fileimage/image/__init__.py
p4a/fileimage/image/_field.py
p4a/fileimage/image/_widget.py
p4a/fileimage/image/configure.zcml