Metadata-Version: 1.0
Name: p4a.fileimage
Version: 1.0.2
Summary: File/Image widget for Zope 3
Home-page: http://pypi.python.org/pypi/p4a.fileimage/
Author: Rocky Burt
Author-email: rocky@serverzen.com
License: GPL
Platform: UNKNOWN
Classifier: Framework :: Zope3
Classifier: Programming Language :: Python
Classifier: License :: OSI Approved :: GNU General Public License (GPL)
Classifier: Topic :: Software Development :: Libraries :: Python Modules
